jassign/__init__.py
jassign/__main__.py
jassign/jassign.py
jassign/jassign_pdf.py
jassign/test.tplx
jassign/to_ok.py
jassign/to_pdf.py
tests/__init__.py
tests/test_export.py
tests/test_strip.py
jassign-0.0.7.dist-info/LICENSE
jassign-0.0.7.dist-info/METADATA
jassign-0.0.7.dist-info/WHEEL
jassign-0.0.7.dist-info/entry_points.txt
jassign-0.0.7.dist-info/top_level.txt
jassign-0.0.7.dist-info/RECORD
