Metadata-Version: 2.1
Name: jassign
Version: 0.0.7
Summary: Jupyter notebook assignment formatting and distribution
Home-page: https://github.com/okpy/jupyter-assignment
Author: John DeNero
Author-email: denero@berkeley.edu
License: UNKNOWN
Platform: UNKNOWN
Classifier: Programming Language :: Python :: 3
Classifier: License :: OSI Approved :: MIT License
Classifier: Operating System :: OS Independent
Requires-Dist: pyyaml
Requires-Dist: nbformat
Requires-Dist: ipython
Requires-Dist: nbconvert
Requires-Dist: tqdm
Requires-Dist: setuptools
